README.md
setup.cfg
setup.py
cgx_notebooks/__init__.py
cgx_notebooks/aaron.py
cgx_notebooks/tanushree.py
cgx_notebooks/vijay.py
cgx_notebooks.egg-info/PKG-INFO
cgx_notebooks.egg-info/SOURCES.txt
cgx_notebooks.egg-info/dependency_links.txt
cgx_notebooks.egg-info/requires.txt
cgx_notebooks.egg-info/top_level.txt