Metadata-Version: 2.1
Name: cgx-notebooks
Version: 1.0.1
Summary: Repository to distribute CloudGenix Python Notebooks and easily install helper functions.
Home-page: https://github.com/ebob9/cgx-notebooks
Author: Aaron Edwards
Author-email: cgx_notebooks@ebob9.com
License: MIT
Platform: UNKNOWN
Classifier: Development Status :: 4 - Beta
Classifier: Intended Audience :: Developers
Classifier: License :: OSI Approved :: MIT License
Classifier: Programming Language :: Python :: 3.6
Classifier: Programming Language :: Python :: 3.7
Classifier: Programming Language :: Python :: 3.8
Requires-Python: >=3.6.1
